my_own_package/__init__.py
Emilio_pack-0.1.0.dist-info/METADATA
Emilio_pack-0.1.0.dist-info/WHEEL
Emilio_pack-0.1.0.dist-info/top_level.txt
Emilio_pack-0.1.0.dist-info/RECORD
