Metadata-Version: 2.1
Name: Emilio-pack
Version: 0.1.0
Summary: Emilio first package
Home-page: UNKNOWN
Author: EmilioPop
Author-email: pop_emilio@yahoo.com
License: UNKNOWN
Platform: UNKNOWN
